faststream_stomp/__init__.py
faststream_stomp/broker.py
faststream_stomp/models.py
faststream_stomp/opentelemetry.py
faststream_stomp/prometheus.py
faststream_stomp/publisher.py
faststream_stomp/py.typed
faststream_stomp/registrator.py
faststream_stomp/router.py
faststream_stomp/subscriber.py
faststream_stomp/testing.py
faststream_stomp-2.2.1.dist-info/METADATA
faststream_stomp-2.2.1.dist-info/WHEEL
faststream_stomp-2.2.1.dist-info/RECORD
