Metadata-Version: 2.4
Name: faststream-stomp
Version: 2.2.1
Summary: FastStream STOMP broker
Project-URL: repository, https://github.com/community-of-python/stompman
Author-email: Lev Vereshchagin <mail@vrslev.com>
License: MIT
Keywords: activemq,artemis,faststream,jms,messaging,stomp
Classifier: Development Status :: 4 - Beta
Classifier: Natural Language :: English
Classifier: Programming Language :: Python :: Implementation :: CPython
Classifier: Topic :: System :: Networking
Classifier: Typing :: Typed
Requires-Python: >=3.11
Requires-Dist: faststream~=0.6
Requires-Dist: stompman>=2.0.1
